any_api/__init__.py
any_api/asyncapi/__init__.py
any_api/asyncapi/asyncapi.py
any_api/asyncapi/model/__init__.py
any_api/asyncapi/model/asyncapi_model.py
any_api/asyncapi/model/operation_model.py
any_api/base_api/__init__.py
any_api/base_api/base_api.py
any_api/base_api/model/__init__.py
any_api/base_api/model/base_api_model.py
any_api/openapi/__init__.py
any_api/openapi/model/__init__.py
any_api/openapi/model/links.py
any_api/openapi/model/openapi/__init__.py
any_api/openapi/model/openapi/basic.py
any_api/openapi/model/openapi/info.py
any_api/openapi/model/openapi/security.py
any_api/openapi/model/requests.py
any_api/openapi/model/responses.py
any_api/openapi/model/util.py
any_api/openapi/openapi.py
any_api/openapi/to/__init__.py
any_api/openapi/to/markdown.py
any_api/openapi/web_ui/__init__.py
any_api/openapi/web_ui/elements.py
any_api/openapi/web_ui/rapidoc.py
any_api/openapi/web_ui/redoc.py
any_api/openapi/web_ui/scalar.py
any_api/openapi/web_ui/swagger.py
any_api/util/__init__.py
any_api/util/i18n.py
any_api/util/pydantic_adapter.py
any_api/util/util.py
any_api-0.1.0.11.dist-info/LICENSE
any_api-0.1.0.11.dist-info/METADATA
any_api-0.1.0.11.dist-info/WHEEL
any_api-0.1.0.11.dist-info/RECORD
